CHANGES.rst
MANIFEST.in
README.rst
bootstrap.py
setup.py
src/experimental/__init__.py
src/experimental.globalgopipindex.egg-info/PKG-INFO
src/experimental.globalgopipindex.egg-info/SOURCES.txt
src/experimental.globalgopipindex.egg-info/dependency_links.txt
src/experimental.globalgopipindex.egg-info/entry_points.txt
src/experimental.globalgopipindex.egg-info/namespace_packages.txt
src/experimental.globalgopipindex.egg-info/not-zip-safe
src/experimental.globalgopipindex.egg-info/requires.txt
src/experimental.globalgopipindex.egg-info/top_level.txt
src/experimental/globalgopipindex/__init__.py
src/experimental/globalgopipindex/catalog.py
src/experimental/globalgopipindex/configure.zcml
src/experimental/globalgopipindex/testing.py
src/experimental/globalgopipindex/tests/__init__.py
src/experimental/globalgopipindex/tests/test_doctest.py