Metadata-Version: 1.1
Name: experimental.globalgopipindex
Version: 1.0.0
Summary: UNKNOWN
Home-page: https://github.com/datakurre/experimental.globalgopipindex
Author: Asko Soukka
Author-email: asko.soukka@iki.fi
License: GPL
Platform: UNKNOWN
Classifier: Programming Language :: Python
Classifier: Programming Language :: Python :: 2.6
Classifier: Programming Language :: Python :: 2.7
Classifier: Framework :: Plone :: 4.1
Classifier: Framework :: Plone :: 4.2
Classifier: Framework :: Plone :: 4.3
